LICENSE.md
README.md
bio_embeddings/__init__.py
bio_embeddings/align/__init__.py
bio_embeddings/align/deepblast.py
bio_embeddings/align/pipeline.py
bio_embeddings/bio_embeddings_schema.json
bio_embeddings/embed/__init__.py
bio_embeddings/embed/bepler_embedder.py
bio_embeddings/embed/cpcprot_embedder.py
bio_embeddings/embed/embedder_interfaces.py
bio_embeddings/embed/esm_embedder.py
bio_embeddings/embed/fasttext_embedder.py
bio_embeddings/embed/glove_embedder.py
bio_embeddings/embed/one_hot_encoding_embedder.py
bio_embeddings/embed/pipeline.py
bio_embeddings/embed/plus_rnn_embedder.py
bio_embeddings/embed/prottrans_albert_bfd_embedder.py
bio_embeddings/embed/prottrans_base_embedder.py
bio_embeddings/embed/prottrans_bert_bfd_embedder.py
bio_embeddings/embed/prottrans_t5_embedder.py
bio_embeddings/embed/prottrans_xlnet_uniref100_embedder.py
bio_embeddings/embed/seqvec_embedder.py
bio_embeddings/embed/unirep_embedder.py
bio_embeddings/embed/word2vec_embedder.py
bio_embeddings/extract/__init__.py
bio_embeddings/extract/annotations/BindingResidues.py
bio_embeddings/extract/annotations/Conservation.py
bio_embeddings/extract/annotations/Disorder.py
bio_embeddings/extract/annotations/Location.py
bio_embeddings/extract/annotations/Membrane.py
bio_embeddings/extract/annotations/SecondaryStructure.py
bio_embeddings/extract/annotations/__init__.py
bio_embeddings/extract/basic/BasicAnnotationExtractor.py
bio_embeddings/extract/basic/__init__.py
bio_embeddings/extract/basic/annotation_inference_models.py
bio_embeddings/extract/bindEmbed21DL/__init__.py
bio_embeddings/extract/bindEmbed21DL/bindEmbed21DL_annotation_extractor.py
bio_embeddings/extract/bindEmbed21DL/binding_residues_cnn.py
bio_embeddings/extract/light_attention/LightAttentionAnnotationExtractor.py
bio_embeddings/extract/light_attention/__init__.py
bio_embeddings/extract/light_attention/light_attention_model.py
bio_embeddings/extract/pipeline.py
bio_embeddings/extract/prott5cons/__init__.py
bio_embeddings-0.2.2.dist-info/entry_points.txt
bio_embeddings-0.2.2.dist-info/LICENSE.md
bio_embeddings-0.2.2.dist-info/WHEEL
bio_embeddings-0.2.2.dist-info/METADATA
bio_embeddings-0.2.2.dist-info/RECORD
