Metadata-Version: 2.1
Name: bio-embeddings
Version: 0.2.2
Summary: A pipeline for protein embedding generation and visualization
License: MIT
Author: Christian Dallago
Author-email: christian.dallago@tum.de
Maintainer: Rostlab
Maintainer-email: admin@rostlab.org
Requires-Python: >=3.7.1,<3.10
Classifier: Intended Audience :: Science/Research
Classifier: License :: OSI Approved :: MIT License
Classifier: Operating System :: OS Independent
Classifier: Programming Language :: Python :: 3
Classifier: Programming Language :: Python :: 3.7
Classifier: Programming Language :: Python :: 3.8
Classifier: Programming Language :: Python :: 3.9
Classifier: Topic :: Scientific/Engineering :: Bio-Informatics
Classifier: Topic :: Scientific/Engineering :: Visualization
Provides-Extra: all
Provides-Extra: bepler
Provides-Extra: cpcprot
Provides-Extra: deepblast
Provides-Extra: esm
Provides-Extra: plus
Provides-Extra: seqvec
Provides-Extra: transformers
Provides-Extra: unirep
Provides-Extra: webserver
Requires-Dist: appdirs (>=1.4.4,<2.0.0)
Requires-Dist: atomicwrites (>=1.4.0,<2.0.0)
Requires-Dist: bio-embeddings-allennlp (==0.9.2); extra == "seqvec" or extra == "all"
Requires-Dist: bio-embeddings-bepler (==0.0.1); extra == "bepler" or extra == "all"
Requires-Dist: bio-embeddings-cpcprot (==0.0.1); extra == "cpcprot" or extra == "all"
Requires-Dist: bio-embeddings-deepblast (==0.1.0); extra == "deepblast" or extra == "all"
Requires-Dist: bio-embeddings-plus (==0.1.1); extra == "plus" or extra == "all"
Requires-Dist: bio-embeddings-tape-proteins (==0.5); extra == "cpcprot" or extra == "all"
Requires-Dist: biopython (>=1.79,<2.0)
Requires-Dist: fair-esm (==0.4.0); extra == "esm" or extra == "all"
Requires-Dist: flask (>=2.0.0,<3.0.0); extra == "webserver"
Requires-Dist: fsspec (==0.8.5); extra == "deepblast"
Requires-Dist: gensim (>=3.8.2,<4.0.0)
Requires-Dist: h5py (>=3.2.1,<4.0.0)
Requires-Dist: humanize (>=3.2.0,<4.0.0)
Requires-Dist: importlib_metadata (>=4.6.1,<5.0.0)
Requires-Dist: jax-unirep (>=1.0.0,<2.0.0); extra == "unirep" or extra == "all"
Requires-Dist: jaxlib (>=0.1.71,<0.2.0); extra == "unirep"
Requires-Dist: lock (>=2018.3.25,<2019.0.0)
Requires-Dist: matplotlib (>=3.2.1,<4.0.0)
Requires-Dist: numpy (>=1.18.3,<2.0.0)
Requires-Dist: pandas (>=1.2.0,<2.0.0)
Requires-Dist: plotly (>=5.1.0,<6.0.0)
Requires-Dist: pymongo (>=3.11.2,<4.0.0); extra == "webserver"
Requires-Dist: python-slugify (>=5.0.2,<6.0.0)
Requires-Dist: ruamel.yaml (>=0.17.10,<0.18.0)
Requires-Dist: scikit-learn (>=0.24.0,<0.25.0)
Requires-Dist: scipy (>=1.4.1,<2.0.0)
Requires-Dist: sentry-sdk[flask] (>=1.0.0,<2.0.0); extra == "webserver"
Requires-Dist: torch (>=1.8.0,<=1.10.0)
Requires-Dist: tqdm (>=4.45.0,<5.0.0)
Requires-Dist: transformers (>=4.5.0,<5.0.0); extra == "transformers" or extra == "all"
Requires-Dist: umap-learn (>=0.5.1,<0.6.0)
Project-URL: homepage, https://visualize.protein.properties
Project-URL: issues, https://github.com/sacdallago/bio_embeddings/issues
Project-URL: repository, https://github.com/sacdallago/bio_embeddings
